setup.py
izigraph/__init__.py
izigraph/base_exporter.py
izigraph/graph.py
izigraph/graph_exporter.py
izigraph/link.py
izigraph/ngv_exporter.py
izigraph/node.py
izigraph.egg-info/PKG-INFO
izigraph.egg-info/SOURCES.txt
izigraph.egg-info/dependency_links.txt
izigraph.egg-info/not-zip-safe
izigraph.egg-info/requires.txt
izigraph.egg-info/top_level.txt
izigraph/importers/__init__.py
izigraph/importers/base_importer.py
izigraph/importers/ngv_importer.py