Metadata-Version: 1.0
Name: izigraph
Version: 0.11.3
Summary: Package to create graphs
Home-page: https://github.com/gnkz/izigraph
Author: Gonzalo Sánchez
Author-email: sanchezv.gonzalo@gmail.com
License: MIT
Platform: UNKNOWN
